wmg_tool/__init__.py
wmg_tool-0.1.0.dist-info/WHEEL
wmg_tool-0.1.0.dist-info/METADATA
wmg_tool-0.1.0.dist-info/RECORD
