Metadata-Version: 2.1
Name: wmg-tool
Version: 0.1.0
Summary: grab content pictures or  videos from social media
Author: wongselent
Requires-Python: >=3.7,<4.0
Classifier: Programming Language :: Python :: 3
Classifier: Programming Language :: Python :: 3.7
Classifier: Programming Language :: Python :: 3.8
Requires-Dist: instaloader (>=4.4.3,<5.0.0)
Requires-Dist: instalooter (>=2.4.2,<3.0.0)
